{
  "generator-jhipster": {
    "applicationType": "monolith",
    "authenticationType": "jwt",
    "baseName": "ecommerce",
    "blueprints": [
      {
        "name": "generator-jhipster-quarkus",
        "version": "3.2.0"
      }
    ],
    "buildTool": "maven",
    "cacheProvider": "no",
    "clientFramework": "angular",
    "clientTestFrameworks": [],
    "clientTheme": "none",
    "creationTimestamp": 1730408453950,
    "databaseType": "sql",
    "devDatabaseType": "h2Memory",
    "devServerPort": 4200,
    "enableHibernateCache": false,
    "enableTranslation": false,
    "entities": [],
    "jhipsterVersion": "8.5.0",
    "microfrontend": null,
    "microfrontends": [],
    "monorepository": true,
    "nativeLanguage": "en",
    "packageName": "com.ecommerce.app",
    "prodDatabaseType": "oracle",
    "serverPort": null,
    "skipCommitHook": true,
    "testFrameworks": [],
    "withAdminUi": true
  }
}
